find_delay/__init__.py
find_delay/find_delay.py
find_delay/private_functions.py
find_delay-2.18.dist-info/METADATA
find_delay-2.18.dist-info/WHEEL
find_delay-2.18.dist-info/licenses/LICENSE
find_delay-2.18.dist-info/RECORD
