Metadata-Version: 2.4
Name: find_delay
Version: 2.18
Summary: Calculate the delay between two arrays
Project-URL: Homepage, https://github.com/RomainPastureau/find_delay
Project-URL: Bug Tracker, https://github.com/RomainPastureau/find_delay/issues
Project-URL: Documentation, https://find-delay.readthedocs.io/en/latest/
Project-URL: PyPI, https://pypi.org/project/find-delay/
Author-email: Romain Pastureau <find_delay@proton.me>
Maintainer-email: Romain Pastureau <find_delay@proton.me>
License-File: LICENSE
Classifier: License :: OSI Approved :: GNU General Public License v3 (GPLv3)
Classifier: Operating System :: OS Independent
Classifier: Programming Language :: Python :: 3
Requires-Python: >=3.7
Requires-Dist: matplotlib>=3.2.0
Requires-Dist: numpy>=1.16.0
Requires-Dist: scipy>=1.5.0
